MANIFEST.in
README.rst
setup.py
QiDataLoader/Bar.py
QiDataLoader/BinaryReader.py
QiDataLoader/DateTimeToOffsetMap.py
QiDataLoader/EnumBarType.py
QiDataLoader/EnumInstrumentType.py
QiDataLoader/FileHeader.py
QiDataLoader/MqDataLoader.py
QiDataLoader/MqDayReader.py
QiDataLoader/MqMinReader.py
QiDataLoader/MqTickReader.py
QiDataLoader/QiCore.py
QiDataLoader/Quote.py
QiDataLoader/Test.py
QiDataLoader/TestTime.py
QiDataLoader/TestTradingDayHelper.py
QiDataLoader/Tick.py
QiDataLoader/TradingDayHelper.py
QiDataLoader/__init__.py
QiDataLoader.egg-info/PKG-INFO
QiDataLoader.egg-info/SOURCES.txt
QiDataLoader.egg-info/dependency_links.txt
QiDataLoader.egg-info/top_level.txt
QiDataLoader/TradingCalendar/2010.tc
QiDataLoader/TradingCalendar/2011.tc
QiDataLoader/TradingCalendar/2012.tc
QiDataLoader/TradingCalendar/2013.tc
QiDataLoader/TradingCalendar/2014.tc
QiDataLoader/TradingCalendar/2015.tc
QiDataLoader/TradingCalendar/2016.tc
QiDataLoader/TradingCalendar/2017.tc
QiDataLoader/TradingCalendar/2018.tc
QiDataLoader/TradingCalendar/2019.tc